ament_cmake_export_dependencies/_dummy.cpython-313-x86_64-linux-gnu.so
ros_ament_cmake_export_dependencies-2.7.3.data/data/share/ament_cmake_export_dependencies/local_setup.bash
ros_ament_cmake_export_dependencies-2.7.3.data/data/share/ament_cmake_export_dependencies/local_setup.dsv
ros_ament_cmake_export_dependencies-2.7.3.data/data/share/ament_cmake_export_dependencies/local_setup.sh
ros_ament_cmake_export_dependencies-2.7.3.data/data/share/ament_cmake_export_dependencies/local_setup.zsh
ros_ament_cmake_export_dependencies-2.7.3.data/data/share/ament_cmake_export_dependencies/package.dsv
ros_ament_cmake_export_dependencies-2.7.3.data/data/share/ament_cmake_export_dependencies/package.xml
ros_ament_cmake_export_dependencies-2.7.3.data/data/share/ament_cmake_export_dependencies/cmake/ament_cmake_export_dependencies-extras.cmake
ros_ament_cmake_export_dependencies-2.7.3.data/data/share/ament_cmake_export_dependencies/cmake/ament_cmake_export_dependencies-extras.cmake.in
ros_ament_cmake_export_dependencies-2.7.3.data/data/share/ament_cmake_export_dependencies/cmake/ament_cmake_export_dependenciesConfig-version.cmake
ros_ament_cmake_export_dependencies-2.7.3.data/data/share/ament_cmake_export_dependencies/cmake/ament_cmake_export_dependenciesConfig.cmake
ros_ament_cmake_export_dependencies-2.7.3.data/data/share/ament_cmake_export_dependencies/cmake/ament_cmake_export_dependencies_package_hook.cmake
ros_ament_cmake_export_dependencies-2.7.3.data/data/share/ament_cmake_export_dependencies/cmake/ament_export_dependencies.cmake
ros_ament_cmake_export_dependencies-2.7.3.data/data/share/ament_cmake_export_dependencies/environment/ament_prefix_path.dsv
ros_ament_cmake_export_dependencies-2.7.3.data/data/share/ament_cmake_export_dependencies/environment/ament_prefix_path.sh
ros_ament_cmake_export_dependencies-2.7.3.data/data/share/ament_cmake_export_dependencies/environment/path.dsv
ros_ament_cmake_export_dependencies-2.7.3.dist-info/METADATA
ros_ament_cmake_export_dependencies-2.7.3.dist-info/WHEEL
ros_ament_cmake_export_dependencies-2.7.3.dist-info/top_level.txt
ros_ament_cmake_export_dependencies-2.7.3.dist-info/RECORD
